README.rst
setup.py
forestutils.egg-info/PKG-INFO
forestutils.egg-info/SOURCES.txt
forestutils.egg-info/dependency_links.txt
forestutils.egg-info/entry_points.txt
forestutils.egg-info/requires.txt
forestutils.egg-info/top_level.txt
src/__init__.py
src/forestutils.py
src/pointcloudfile.py