Metadata-Version: 1.1
Name: forestutils
Version: 0.2.1
Summary: Tools to analyse 3D scans of a forest.
Home-page: https://github.com/borevitzlab/3D-tools
Author: Zac Hatfield-Dodds
Author-email: zac.hatfield.dodds@gmail.com
License: GPL3+
Keywords: forest LIDAR photogrammetery environment remote-sensing
Platform: UNKNOWN
Classifier: Development Status :: 3 - Alpha
Classifier: Environment :: Console
Classifier: Intended Audience :: Science/Research
Classifier: License :: OSI Approved :: GNU General Public License v3 or later (GPLv3+)
Classifier: Natural Language :: English
Classifier: Operating System :: OS Independent
Classifier: Programming Language :: Python :: 3
Classifier: Programming Language :: Python :: 3.4
Classifier: Programming Language :: Python :: 3.5
Classifier: Topic :: Scientific/Engineering :: Bio-Informatics
Classifier: Topic :: Scientific/Engineering :: Visualization
